gssheet26/__init__.py
gssheet26-0.0.2.dist-info/LICENSE.txt
gssheet26-0.0.2.dist-info/METADATA
gssheet26-0.0.2.dist-info/WHEEL
gssheet26-0.0.2.dist-info/top_level.txt
gssheet26-0.0.2.dist-info/RECORD
