Metadata-Version: 2.1
Name: gssheet26
Version: 0.0.2
Summary: This is a python package which helps to read the data from Google Spreadsheets.
Home-page: https://github.com/NikhilShrivastava/Greendeck-Assignment
Author: Nikhil Shrivastava
Author-email: nikhilshrivastava175@gmail.com
License: MIT
Platform: UNKNOWN
Classifier: Programming Language :: Python :: 3
Classifier: License :: OSI Approved :: MIT License
Classifier: Operating System :: Microsoft :: Windows :: Windows 10
Requires-Dist: gspread
Requires-Dist: oauth2client
Requires-Dist: pandas
Requires-Dist: matplotlib
